jellyash/__init__.py
jellyash/bundle.py
jellyash/cli.py
jellyash/client.py
jellyash/duration.py
jellyash/nextup.py
jellyash/search.py
jellyash/token.py
jellyash/unwatched.py
jellyash-0.6.0.dist-info/METADATA
jellyash-0.6.0.dist-info/WHEEL
jellyash-0.6.0.dist-info/entry_points.txt
jellyash-0.6.0.dist-info/licenses/LICENSE
jellyash-0.6.0.dist-info/RECORD
