Metadata-Version: 2.3
Name: jellyash
Version: 0.6.0
Project-URL: Source, https://github.com/s-t-e-v-e-n-k/jellyash
License: Copyright 2023 Steve Kowalik <steven@wedontsleep.org>
License-File: LICENSE
Requires-Python: >=3.8
Requires-Dist: jellyfin-apiclient-python
Requires-Dist: typing-extensions; python_version < '3.11'
